dye_score/__init__.py
dye_score/distances.py
dye_score/dye_score.py
dye_score/plotting.py
dye_score/utils.py
dye_score-0.11.3.dist-info/LICENSE
dye_score-0.11.3.dist-info/METADATA
dye_score-0.11.3.dist-info/WHEEL
dye_score-0.11.3.dist-info/top_level.txt
dye_score-0.11.3.dist-info/RECORD
